ks_market_api/__about__.py
ks_market_api/__init__.py
ks_market_api/api.py
ks_market_api/config.py
ks_market_api/logger.py
ks_market_api-1.2.1.dist-info/METADATA
ks_market_api-1.2.1.dist-info/WHEEL
ks_market_api-1.2.1.dist-info/RECORD
