Metadata-Version: 2.4
Name: ks_market_api
Version: 1.2.1
License-Expression: MIT
Requires-Python: >=3.8
Requires-Dist: ks-futu-market-api>=1.0.13
Requires-Dist: ks-trade-api>=0.1.0
Requires-Dist: ks-utility>=0.0.35
